{
  "author": "Light Rail Transit Authority (LRTA)", 
  "author_email": "", 
  "download_url": "http://storage.googleapis.com/amt-dgph.appspot.com/uploads/aJRHOce8WhBj7HyZ1RNl/2010_lrt_1_monthly_average_by_day_out.csv", 
  "extras": {
    "Frequency Update": "Monthly", 
    "Granularity": "National", 
    "Temporal Date": "01/01/10-12/31/14"
  }, 
  "id": "f5fc9935-d9e8-4855-8369-ccbab9818566", 
  "license": "Open Data Commons Attribution License", 
  "maintainer": "Management Information System Division", 
  "maintainer_email": "mis_icc@lrta.gov.ph", 
  "name": "light-rail-transit-line-1---daily-and-monthly-passenger-traffic-average-per-station---by-day-out", 
  "notes": "This data set contains the daily and monthly number of passengers who have entered and exited per station (by day out) in Light Rail Transit (LRT) Line 1 in 2010-2014.", 
  "relationships": [], 
  "resources": [
    {
      "cache_last_updated": null, 
      "cache_url": null, 
      "created": "2016-03-29T14:44:45.263713", 
      "description": "Contains daily and monthly data on passenger traffic on Light Rail Transit (LRT) Line 1, from Roosevelt to Baclaran.", 
      "format": "CSV", 
      "hash": "", 
      "id": "08f5c1af-d542-4d2a-9125-fa37689413f8", 
      "last_modified": null, 
      "mimetype": null, 
      "mimetype_inner": null, 
      "name": "LRT LINE 1 - 2010 DAILY AND MONTHLY PASSENGER TRAFFIC PER STATION (BY DAY OUT)", 
      "package_id": "f5fc9935-d9e8-4855-8369-ccbab9818566", 
      "position": 0, 
      "resource_group_id": "4e940a79-2999-4742-992e-af6ec4528dc4", 
      "resource_type": null, 
      "size": null, 
      "url": "http://storage.googleapis.com/amt-dgph.appspot.com/uploads/aJRHOce8WhBj7HyZ1RNl/2010_lrt_1_monthly_average_by_day_out.csv", 
      "url_type": null, 
      "webstore_last_updated": null, 
      "webstore_url": null
    }, 
    {
      "cache_last_updated": null, 
      "cache_url": null, 
      "created": "2016-03-29T14:44:49.141994", 
      "description": "Contains daily and monthly data on passenger traffic on Light Rail Transit (LRT) Line 1, from Roosevelt to Baclaran.", 
      "format": "CSV", 
      "hash": "", 
      "id": "dc28814e-bc09-48d3-a990-157a6210eeb3", 
      "last_modified": null, 
      "mimetype": null, 
      "mimetype_inner": null, 
      "name": "LRT LINE 1 - 2011 DAILY AND MONTHLY PASSENGER TRAFFIC PER STATION (BY DAY OUT)", 
      "package_id": "f5fc9935-d9e8-4855-8369-ccbab9818566", 
      "position": 1, 
      "resource_group_id": "4e940a79-2999-4742-992e-af6ec4528dc4", 
      "resource_type": null, 
      "size": null, 
      "url": "http://storage.googleapis.com/amt-dgph.appspot.com/uploads/Mt7jSU4YQjTqXZRm5O6q/2011_lrt_1_monthly_average_by_day_out.csv", 
      "url_type": null, 
      "webstore_last_updated": null, 
      "webstore_url": null
    }, 
    {
      "cache_last_updated": null, 
      "cache_url": null, 
      "created": "2016-03-29T14:44:53.053916", 
      "description": "Contains daily and monthly data on passenger traffic on Light Rail Transit (LRT) Line 1, from Roosevelt to Baclaran.", 
      "format": "CSV", 
      "hash": "", 
      "id": "ac819832-ba6c-4e76-8bad-ba1ccdf289c5", 
      "last_modified": null, 
      "mimetype": null, 
      "mimetype_inner": null, 
      "name": "LRT LINE 1 - 2012 DAILY AND MONTHLY PASSENGER TRAFFIC PER STATION (BY DAY OUT)", 
      "package_id": "f5fc9935-d9e8-4855-8369-ccbab9818566", 
      "position": 2, 
      "resource_group_id": "4e940a79-2999-4742-992e-af6ec4528dc4", 
      "resource_type": null, 
      "size": null, 
      "url": "http://storage.googleapis.com/amt-dgph.appspot.com/uploads/ZHoQ0fVpnKzjITHYS551/2012_lrt_1_monthly_average_by_day_out.csv", 
      "url_type": null, 
      "webstore_last_updated": null, 
      "webstore_url": null
    }, 
    {
      "cache_last_updated": null, 
      "cache_url": null, 
      "created": "2016-03-29T14:44:57.919027", 
      "description": "Contains daily and monthly data on passenger traffic on Light Rail Transit (LRT) Line 1, from Roosevelt to Baclaran.", 
      "format": "CSV", 
      "hash": "", 
      "id": "51c93951-93cc-4e7c-96cc-593692188bdd", 
      "last_modified": null, 
      "mimetype": null, 
      "mimetype_inner": null, 
      "name": "LRT LINE 1 - 2013 DAILY AND MONTHLY PASSENGER TRAFFIC PER STATION (BY DAY OUT)", 
      "package_id": "f5fc9935-d9e8-4855-8369-ccbab9818566", 
      "position": 3, 
      "resource_group_id": "4e940a79-2999-4742-992e-af6ec4528dc4", 
      "resource_type": null, 
      "size": null, 
      "url": "http://storage.googleapis.com/amt-dgph.appspot.com/uploads/6hOLtQTBzRdP26lSqxz9/2013_lrt_1_monthly_average_by_day_out.csv", 
      "url_type": null, 
      "webstore_last_updated": null, 
      "webstore_url": null
    }, 
    {
      "cache_last_updated": null, 
      "cache_url": null, 
      "created": "2016-03-29T14:45:02.244893", 
      "description": "Contains daily and monthly data on passenger traffic on Light Rail Transit (LRT) Line 1, from Roosevelt to Baclaran.", 
      "format": "CSV", 
      "hash": "", 
      "id": "a471b777-3ab8-4862-be0f-f4fbb4bd1969", 
      "last_modified": null, 
      "mimetype": null, 
      "mimetype_inner": null, 
      "name": "LRT LINE 1 - 2014 DAILY AND MONTHLY PASSENGER TRAFFIC PER STATION (BY DAY IN)", 
      "package_id": "f5fc9935-d9e8-4855-8369-ccbab9818566", 
      "position": 4, 
      "resource_group_id": "4e940a79-2999-4742-992e-af6ec4528dc4", 
      "resource_type": null, 
      "size": null, 
      "url": "http://storage.googleapis.com/amt-dgph.appspot.com/uploads/euOABF93k87aO2IFt04G/2014_lrt_1_monthly_average_day_out.csv", 
      "url_type": null, 
      "webstore_last_updated": null, 
      "webstore_url": null
    }
  ], 
  "tags": [], 
  "title": "LIGHT RAIL TRANSIT LINE 1 - DAILY AND MONTHLY PASSENGER TRAFFIC AVERAGE PER STATION - BY DAY OUT", 
  "url": null, 
  "version": null
}