{
  "author": "Bangko Sentral ng Pilipinas", 
  "author_email": "bspmail@bsp.gov.ph", 
  "download_url": "http://storage.googleapis.com/amt-dgph.appspot.com/uploads/ANF1qXr8RiOuybkO3vnH/metho_bes.docx", 
  "extras": {
    "Frequency Update": "Quarterly", 
    "Granularity": "National", 
    "Temporal Date": "06/31/2010-03/31/2015"
  }, 
  "id": "53c378b5-fd05-434b-9e46-eaac43b89260", 
  "license": "Open Data Commons Attribution License", 
  "maintainer": "Expectations Survey and Leading Indicators Group (ESLIG)", 
  "maintainer_email": "esligdes@bsp.gov.ph", 
  "name": "business-expectations-survey", 
  "notes": "This dataset contains the results of the survey to provide advance information on the current and near-term economic and business conditions, and other indicators of aggregate demand that are useful inputs for the formulation of monetary policy including levels of production and economic activity as well as factors that could influence the movement of key economic variables namely, Gross Domestic Product (GDP), interest rate, peso/dollar exchange rate and inflation rate.", 
  "relationships": [], 
  "resources": [
    {
      "cache_last_updated": null, 
      "cache_url": null, 
      "created": "2015-09-15T10:12:47.216952", 
      "description": "", 
      "format": "DOCX", 
      "hash": "", 
      "id": "fde6299d-d0e5-4cdc-9fe2-e6bdfa5a795a", 
      "last_modified": null, 
      "mimetype": null, 
      "mimetype_inner": null, 
      "name": "Methodology", 
      "package_id": "53c378b5-fd05-434b-9e46-eaac43b89260", 
      "position": 0, 
      "resource_group_id": "4dd4db6e-7294-4995-a980-2e6b98ab1091", 
      "resource_type": null, 
      "size": null, 
      "url": "http://storage.googleapis.com/amt-dgph.appspot.com/uploads/ANF1qXr8RiOuybkO3vnH/metho_bes.docx", 
      "url_type": null, 
      "webstore_last_updated": null, 
      "webstore_url": null
    }, 
    {
      "cache_last_updated": null, 
      "cache_url": null, 
      "created": "2015-09-15T10:12:48.093123", 
      "description": " ", 
      "format": "PDF", 
      "hash": "", 
      "id": "c1866103-cae6-476e-8c8e-3337dcb8299c", 
      "last_modified": null, 
      "mimetype": null, 
      "mimetype_inner": null, 
      "name": "Business Expectation Survey 2014", 
      "package_id": "53c378b5-fd05-434b-9e46-eaac43b89260", 
      "position": 1, 
      "resource_group_id": "4dd4db6e-7294-4995-a980-2e6b98ab1091", 
      "resource_type": null, 
      "size": null, 
      "url": "http://www.bsp.gov.ph/downloads/Publications/2014/BES_1qtr2014.pdf", 
      "url_type": null, 
      "webstore_last_updated": null, 
      "webstore_url": null
    }
  ], 
  "tags": [], 
  "title": "Business Expectations Survey", 
  "url": null, 
  "version": null
}