{
  "author": "Bangko Sentral ng Pilipinas", 
  "author_email": "bspmail@bsp.gov.ph", 
  "download_url": "http://www.bsp.gov.ph/statistics/spei_pub/Table 37.pdf", 
  "extras": {
    "Frequency Update": "Monthly", 
    "Granularity": "National", 
    "Temporal Date": "01/01/1989-06/30/2015"
  }, 
  "id": "7d740bab-6514-44bb-bca6-7b9932ab96b4", 
  "license": "Open Data Commons Attribution License", 
  "maintainer": "Expectations Survey and Leading Indicators Group (ESLIG)", 
  "maintainer_email": "esligdes@bsp.gov.ph", 
  "name": "retail-price-index-2015", 
  "notes": "This dataset contains the Retail Price Index (RPI), the indicator of the changes in the prices at which retailers dispose of their goods to consumers or end-users relative to a base year. It is used as a deflator of the National Accounts in the retail trade sector and serves as a basis for forecasting business in the retail trade.", 
  "relationships": [], 
  "resources": [
    {
      "cache_last_updated": null, 
      "cache_url": null, 
      "created": "2015-09-14T13:16:18.136697", 
      "description": "", 
      "format": "PDF", 
      "hash": "", 
      "id": "3fdfda9f-5559-4462-8d55-4b2faa481961", 
      "last_modified": null, 
      "mimetype": null, 
      "mimetype_inner": null, 
      "name": "Current Reporting Period", 
      "package_id": "7d740bab-6514-44bb-bca6-7b9932ab96b4", 
      "position": 0, 
      "resource_group_id": "13f12b8b-c6b2-4f92-9000-861f784a3205", 
      "resource_type": null, 
      "size": null, 
      "url": "http://www.bsp.gov.ph/statistics/spei_pub/Table 37.pdf", 
      "url_type": null, 
      "webstore_last_updated": null, 
      "webstore_url": null
    }, 
    {
      "cache_last_updated": null, 
      "cache_url": null, 
      "created": "2015-09-14T13:16:25.174003", 
      "description": "", 
      "format": "DOCX", 
      "hash": "", 
      "id": "d1a3ad62-7042-4316-8da9-3ad95e9cf0e6", 
      "last_modified": null, 
      "mimetype": null, 
      "mimetype_inner": null, 
      "name": "Methodology", 
      "package_id": "7d740bab-6514-44bb-bca6-7b9932ab96b4", 
      "position": 1, 
      "resource_group_id": "13f12b8b-c6b2-4f92-9000-861f784a3205", 
      "resource_type": null, 
      "size": null, 
      "url": "http://storage.googleapis.com/amt-dgph.appspot.com/uploads/SvcRe4tv6gI3GVmLSqPu/metho_retail_price_index.docx", 
      "url_type": null, 
      "webstore_last_updated": null, 
      "webstore_url": null
    }, 
    {
      "cache_last_updated": null, 
      "cache_url": null, 
      "created": "2015-09-14T13:16:28.060646", 
      "description": "", 
      "format": "XLS", 
      "hash": "", 
      "id": "0f757eb2-0ec7-4bf6-b542-ef21db02c2ae", 
      "last_modified": null, 
      "mimetype": null, 
      "mimetype_inner": null, 
      "name": "Historical Data Series", 
      "package_id": "7d740bab-6514-44bb-bca6-7b9932ab96b4", 
      "position": 2, 
      "resource_group_id": "13f12b8b-c6b2-4f92-9000-861f784a3205", 
      "resource_type": null, 
      "size": null, 
      "url": "http://www.bsp.gov.ph/statistics/excel/rpi.xls", 
      "url_type": null, 
      "webstore_last_updated": null, 
      "webstore_url": null
    }
  ], 
  "tags": [], 
  "title": "Retail Price Index 2015", 
  "url": null, 
  "version": null
}