{
  "author": "Bureau of Local Government Supervision", 
  "author_email": "blgs.lgpms@gmail.com", 
  "download_url": "http://storage.googleapis.com/amt-dgph.appspot.com/uploads/FXnoCV4nqnb7zMGRIsXD/cabadbaran_ira_utilization_201303_q1_1.csv", 
  "extras": {
    "Granularity": "City or Municipality", 
    "Temporal Date": "01/01/2013-09/30/2014"
  }, 
  "id": "364fa37c-4b8c-407e-bc72-2d1a3facc5c8", 
  "license": "Open Data Commons Attribution License", 
  "maintainer": "", 
  "maintainer_email": "", 
  "name": "internal-revenue-allotment-utilization-of-cabadbaran-city", 
  "notes": "This dataset contains report of the internal revenue allotment utilization of Cabadbaran City.", 
  "relationships": [], 
  "resources": [
    {
      "cache_last_updated": null, 
      "cache_url": null, 
      "created": "2015-12-16T14:14:00.945949", 
      "description": "", 
      "format": "CSV", 
      "hash": "", 
      "id": "2128e825-aee5-4bb7-a537-f40d15e34a60", 
      "last_modified": null, 
      "mimetype": null, 
      "mimetype_inner": null, 
      "name": "2013 Quarter 1 - Cabadbaran City IRAU", 
      "package_id": "364fa37c-4b8c-407e-bc72-2d1a3facc5c8", 
      "position": 0, 
      "resource_group_id": "bb0bf4aa-30ba-4795-a983-e810cc908072", 
      "resource_type": null, 
      "size": null, 
      "url": "http://storage.googleapis.com/amt-dgph.appspot.com/uploads/FXnoCV4nqnb7zMGRIsXD/cabadbaran_ira_utilization_201303_q1_1.csv", 
      "url_type": null, 
      "webstore_last_updated": null, 
      "webstore_url": null
    }, 
    {
      "cache_last_updated": null, 
      "cache_url": null, 
      "created": "2015-12-16T14:14:04.436086", 
      "description": "", 
      "format": "CSV", 
      "hash": "", 
      "id": "39fdc77e-d23c-4b5f-b7b8-22857f5e8b3c", 
      "last_modified": null, 
      "mimetype": null, 
      "mimetype_inner": null, 
      "name": "2013 Quarter 2 - Cabadbaran City IRAU", 
      "package_id": "364fa37c-4b8c-407e-bc72-2d1a3facc5c8", 
      "position": 1, 
      "resource_group_id": "bb0bf4aa-30ba-4795-a983-e810cc908072", 
      "resource_type": null, 
      "size": null, 
      "url": "http://storage.googleapis.com/amt-dgph.appspot.com/uploads/T3cvtEJ1uOLMYC444qcU/cabadbaran_ira_utilization_20130630_q2_1.csv", 
      "url_type": null, 
      "webstore_last_updated": null, 
      "webstore_url": null
    }, 
    {
      "cache_last_updated": null, 
      "cache_url": null, 
      "created": "2015-12-16T14:14:07.883533", 
      "description": "", 
      "format": "CSV", 
      "hash": "", 
      "id": "2b6eadba-5c44-40d7-a064-2d8f3460d3ee", 
      "last_modified": null, 
      "mimetype": null, 
      "mimetype_inner": null, 
      "name": "2014 Quarter 2 - Cabadbaran City IRAU", 
      "package_id": "364fa37c-4b8c-407e-bc72-2d1a3facc5c8", 
      "position": 2, 
      "resource_group_id": "bb0bf4aa-30ba-4795-a983-e810cc908072", 
      "resource_type": null, 
      "size": null, 
      "url": "http://storage.googleapis.com/amt-dgph.appspot.com/uploads/fsqomHtY2N39tcrFzCVs/cabadbaran_ira_utilization_20140630_q2.csv", 
      "url_type": null, 
      "webstore_last_updated": null, 
      "webstore_url": null
    }, 
    {
      "cache_last_updated": null, 
      "cache_url": null, 
      "created": "2015-12-16T14:14:11.456766", 
      "description": "", 
      "format": "CSV", 
      "hash": "", 
      "id": "4f3ce975-600b-42eb-9be7-93a9b78324bb", 
      "last_modified": null, 
      "mimetype": null, 
      "mimetype_inner": null, 
      "name": "2014 Quarter 1 - Cabadbaran City IRAU", 
      "package_id": "364fa37c-4b8c-407e-bc72-2d1a3facc5c8", 
      "position": 3, 
      "resource_group_id": "bb0bf4aa-30ba-4795-a983-e810cc908072", 
      "resource_type": null, 
      "size": null, 
      "url": "http://storage.googleapis.com/amt-dgph.appspot.com/uploads/BfVImeKP2j57ECw0riHp/cabadbaran_ira_utilization_20140331_q1.csv", 
      "url_type": null, 
      "webstore_last_updated": null, 
      "webstore_url": null
    }, 
    {
      "cache_last_updated": null, 
      "cache_url": null, 
      "created": "2015-12-16T14:14:15.327706", 
      "description": "", 
      "format": "CSV", 
      "hash": "", 
      "id": "1e592547-47f9-4acd-a272-ff852cc20017", 
      "last_modified": null, 
      "mimetype": null, 
      "mimetype_inner": null, 
      "name": "2013 Quarter 4 - Cabadbaran City IRAU", 
      "package_id": "364fa37c-4b8c-407e-bc72-2d1a3facc5c8", 
      "position": 4, 
      "resource_group_id": "bb0bf4aa-30ba-4795-a983-e810cc908072", 
      "resource_type": null, 
      "size": null, 
      "url": "http://storage.googleapis.com/amt-dgph.appspot.com/uploads/pZPZk8pTsWodm9YIeHwe/cabadbaran_ira_utilization_20131231_q4_1.csv", 
      "url_type": null, 
      "webstore_last_updated": null, 
      "webstore_url": null
    }, 
    {
      "cache_last_updated": null, 
      "cache_url": null, 
      "created": "2015-12-16T14:14:19.604385", 
      "description": "", 
      "format": "CSV", 
      "hash": "", 
      "id": "668f1747-45a0-4161-81f8-05afba41f118", 
      "last_modified": null, 
      "mimetype": null, 
      "mimetype_inner": null, 
      "name": "2013 Quarter 3 - Cabadbaran City IRAU", 
      "package_id": "364fa37c-4b8c-407e-bc72-2d1a3facc5c8", 
      "position": 5, 
      "resource_group_id": "bb0bf4aa-30ba-4795-a983-e810cc908072", 
      "resource_type": null, 
      "size": null, 
      "url": "http://storage.googleapis.com/amt-dgph.appspot.com/uploads/O8e7bEZNt2LttitFyjte/cabadbaran_ira_utilization_20130930_q3_1.csv", 
      "url_type": null, 
      "webstore_last_updated": null, 
      "webstore_url": null
    }, 
    {
      "cache_last_updated": null, 
      "cache_url": null, 
      "created": "2015-12-16T14:14:23.840271", 
      "description": "", 
      "format": "CSV", 
      "hash": "", 
      "id": "702bcba9-07f1-44ae-b2d9-b87e7bda7533", 
      "last_modified": null, 
      "mimetype": null, 
      "mimetype_inner": null, 
      "name": "2014 Quarter 4 - Cabadbaran City IRAU", 
      "package_id": "364fa37c-4b8c-407e-bc72-2d1a3facc5c8", 
      "position": 6, 
      "resource_group_id": "bb0bf4aa-30ba-4795-a983-e810cc908072", 
      "resource_type": null, 
      "size": null, 
      "url": "http://storage.googleapis.com/amt-dgph.appspot.com/uploads/Tx6n6kFzqBxCXpaKqvoZ/cabadbaran_ira_utilization_20140930_q3.csv", 
      "url_type": null, 
      "webstore_last_updated": null, 
      "webstore_url": null
    }
  ], 
  "tags": [
    "Local Government"
  ], 
  "title": "INTERNAL REVENUE ALLOTMENT UTILIZATION OF CABADBARAN CITY", 
  "url": "", 
  "version": ""
}