{
  "author": "Bureau of Soils and Water Management", 
  "author_email": "bswmclientcenter@yahoo.com", 
  "download_url": "http://bswm.maps.da.gov.ph/maps/download/Camarines_Nor_LMU1/Camarines_Nor_LMU1.zip", 
  "extras": {
    "Frequency of Update": "Annually", 
    "Granularity": "Province", 
    "Temporal Date": ""
  }, 
  "id": "037ad6f4-5c2e-452a-8611-1701349931fa", 
  "license": "Open Data Commons Attribution License", 
  "maintainer": "Dr. Gina Nilo", 
  "maintainer_email": "ginapnilo@ymail.com", 
  "name": "land-management-unit-map-for-camarines-norte", 
  "notes": "Land Management Unit Map (LMU) - is a delineation of a recurring pattern of similar landform and parent material with relatively homogeneous soil characteristics, qualities and land use/vegetation.\r\nMap Type:\tLand Management Unit Map\t\r\nIsland:\tLuzon\r\nRegion:\tRegion V\r\nScale:\t50000\r\nProvince:\tCamarines Norte", 
  "relationships": [], 
  "resources": [
    {
      "cache_last_updated": null, 
      "cache_url": null, 
      "created": "2014-11-24T11:36:42.651861", 
      "description": "", 
      "format": "SHP", 
      "hash": "", 
      "id": "adf29641-7920-4be4-9b48-614ec7b02e28", 
      "last_modified": null, 
      "mimetype": null, 
      "mimetype_inner": null, 
      "name": "Land Management Unit Map_Camarines Northe1", 
      "package_id": "037ad6f4-5c2e-452a-8611-1701349931fa", 
      "position": 0, 
      "resource_group_id": "ca33d4e8-d6de-4fdd-a672-f02f01675570", 
      "resource_type": null, 
      "size": null, 
      "url": "http://bswm.maps.da.gov.ph/maps/download/Camarines_Nor_LMU1/Camarines_Nor_LMU1.zip", 
      "url_type": null, 
      "webstore_last_updated": null, 
      "webstore_url": null
    }, 
    {
      "cache_last_updated": null, 
      "cache_url": null, 
      "created": "2014-11-24T11:37:08.951058", 
      "description": "", 
      "format": "SHP", 
      "hash": "", 
      "id": "ab1ba11f-cf7a-4419-acde-5cced793d37e", 
      "last_modified": null, 
      "mimetype": null, 
      "mimetype_inner": null, 
      "name": "Land Management Unit Map_Camarines Northe10", 
      "package_id": "037ad6f4-5c2e-452a-8611-1701349931fa", 
      "position": 1, 
      "resource_group_id": "ca33d4e8-d6de-4fdd-a672-f02f01675570", 
      "resource_type": null, 
      "size": null, 
      "url": "http://bswm.maps.da.gov.ph/maps/download/Camarines_Nor_LMU10/Camarines_Nor_LMU10.zip", 
      "url_type": null, 
      "webstore_last_updated": null, 
      "webstore_url": null
    }, 
    {
      "cache_last_updated": null, 
      "cache_url": null, 
      "created": "2014-11-24T11:37:33.370897", 
      "description": "", 
      "format": "SHP", 
      "hash": "", 
      "id": "f1050081-22c5-443d-be20-4491c3107c5b", 
      "last_modified": null, 
      "mimetype": null, 
      "mimetype_inner": null, 
      "name": "Land Management Unit Map_Camarines Northe3", 
      "package_id": "037ad6f4-5c2e-452a-8611-1701349931fa", 
      "position": 2, 
      "resource_group_id": "ca33d4e8-d6de-4fdd-a672-f02f01675570", 
      "resource_type": null, 
      "size": null, 
      "url": "http://bswm.maps.da.gov.ph/maps/download/Camarines_Nor_LMU3/Camarines_Nor_LMU3.zip", 
      "url_type": null, 
      "webstore_last_updated": null, 
      "webstore_url": null
    }, 
    {
      "cache_last_updated": null, 
      "cache_url": null, 
      "created": "2014-11-24T11:38:03.110413", 
      "description": "", 
      "format": "SHP", 
      "hash": "", 
      "id": "c690379f-94e8-4cf1-a50f-3d272c19ea2e", 
      "last_modified": null, 
      "mimetype": null, 
      "mimetype_inner": null, 
      "name": "Land Management Unit Map_Camarines Northe4", 
      "package_id": "037ad6f4-5c2e-452a-8611-1701349931fa", 
      "position": 3, 
      "resource_group_id": "ca33d4e8-d6de-4fdd-a672-f02f01675570", 
      "resource_type": null, 
      "size": null, 
      "url": "http://bswm.maps.da.gov.ph/maps/download/Camarines_Nor_LMU4/Camarines_Nor_LMU4.zip", 
      "url_type": null, 
      "webstore_last_updated": null, 
      "webstore_url": null
    }, 
    {
      "cache_last_updated": null, 
      "cache_url": null, 
      "created": "2014-11-24T11:38:23.019148", 
      "description": "", 
      "format": "SHP", 
      "hash": "", 
      "id": "4dba2948-a19f-457b-a82a-6e984a124547", 
      "last_modified": null, 
      "mimetype": null, 
      "mimetype_inner": null, 
      "name": "Land Management Unit Map_Camarines Northe5", 
      "package_id": "037ad6f4-5c2e-452a-8611-1701349931fa", 
      "position": 4, 
      "resource_group_id": "ca33d4e8-d6de-4fdd-a672-f02f01675570", 
      "resource_type": null, 
      "size": null, 
      "url": "http://bswm.maps.da.gov.ph/maps/download/Camarines_Nor_LMU5/Camarines_Nor_LMU5.zip", 
      "url_type": null, 
      "webstore_last_updated": null, 
      "webstore_url": null
    }, 
    {
      "cache_last_updated": null, 
      "cache_url": null, 
      "created": "2014-11-24T11:38:49.528818", 
      "description": "", 
      "format": "SHP", 
      "hash": "", 
      "id": "b30a9d38-e8e0-442a-836b-3c14dcc4d179", 
      "last_modified": null, 
      "mimetype": null, 
      "mimetype_inner": null, 
      "name": "Land Management Unit Map_Camarines Northe6", 
      "package_id": "037ad6f4-5c2e-452a-8611-1701349931fa", 
      "position": 5, 
      "resource_group_id": "ca33d4e8-d6de-4fdd-a672-f02f01675570", 
      "resource_type": null, 
      "size": null, 
      "url": "http://bswm.maps.da.gov.ph/maps/download/Camarines_Nor_LMU6/Camarines_Nor_LMU6.zip", 
      "url_type": null, 
      "webstore_last_updated": null, 
      "webstore_url": null
    }, 
    {
      "cache_last_updated": null, 
      "cache_url": null, 
      "created": "2014-11-24T11:39:13.203567", 
      "description": "", 
      "format": "SHP", 
      "hash": "", 
      "id": "9a4a6861-058c-4920-83e9-940a95baba78", 
      "last_modified": null, 
      "mimetype": null, 
      "mimetype_inner": null, 
      "name": "Land Management Unit Map_Camarines Northe7", 
      "package_id": "037ad6f4-5c2e-452a-8611-1701349931fa", 
      "position": 6, 
      "resource_group_id": "ca33d4e8-d6de-4fdd-a672-f02f01675570", 
      "resource_type": null, 
      "size": null, 
      "url": "http://bswm.maps.da.gov.ph/maps/download/Camarines_Nor_LMU7/Camarines_Nor_LMU7.zip", 
      "url_type": null, 
      "webstore_last_updated": null, 
      "webstore_url": null
    }, 
    {
      "cache_last_updated": null, 
      "cache_url": null, 
      "created": "2014-11-24T11:39:32.856327", 
      "description": "", 
      "format": "SHP", 
      "hash": "", 
      "id": "bbd95021-aa98-4fe3-a050-7ce9b340e95d", 
      "last_modified": null, 
      "mimetype": null, 
      "mimetype_inner": null, 
      "name": "Land Management Unit Map_Camarines Northe8", 
      "package_id": "037ad6f4-5c2e-452a-8611-1701349931fa", 
      "position": 7, 
      "resource_group_id": "ca33d4e8-d6de-4fdd-a672-f02f01675570", 
      "resource_type": null, 
      "size": null, 
      "url": "http://bswm.maps.da.gov.ph/maps/download/Camarines_Nor_LMU8/Camarines_Nor_LMU8.zip", 
      "url_type": null, 
      "webstore_last_updated": null, 
      "webstore_url": null
    }, 
    {
      "cache_last_updated": null, 
      "cache_url": null, 
      "created": "2014-11-24T11:39:57.484516", 
      "description": "", 
      "format": "SHP", 
      "hash": "", 
      "id": "236581cf-0be3-4f86-95b7-a79533968b81", 
      "last_modified": null, 
      "mimetype": null, 
      "mimetype_inner": null, 
      "name": "Land Management Unit Map_Camarines Northe9", 
      "package_id": "037ad6f4-5c2e-452a-8611-1701349931fa", 
      "position": 8, 
      "resource_group_id": "ca33d4e8-d6de-4fdd-a672-f02f01675570", 
      "resource_type": null, 
      "size": null, 
      "url": "http://bswm.maps.da.gov.ph/maps/download/Camarines_Nor_LMU9/Camarines_Nor_LMU9.zip", 
      "url_type": null, 
      "webstore_last_updated": null, 
      "webstore_url": null
    }
  ], 
  "tags": [
    "Geospatial"
  ], 
  "title": "Land Management Unit Map for Camarines Norte", 
  "url": "http://bswm.maps.da.gov.ph/", 
  "version": ""
}