{
  "author": "Bureau of Local Government Supervision", 
  "author_email": "blgs.lgpms@gmail.com", 
  "download_url": "http://storage.googleapis.com/amt-dgph.appspot.com/uploads/QRomxtuyZNd7EdKiiqkl/surigaodelnorte_ira_utilization_20%_09302014_q3.csv", 
  "extras": {
    "Granularity": "Province", 
    "Temporal Date": "01/01/2012-06/30/2012, 01/01/2013-09/30/2014"
  }, 
  "id": "30d64e00-99cd-435b-9e66-969a689fa300", 
  "license": "Open Data Commons Attribution License", 
  "maintainer": "", 
  "maintainer_email": "", 
  "name": "internal-revenue-allotment-utilization-of-surigao-del-norte-province", 
  "notes": "This dataset contains report of the internal revenue allotment utilization of Surigao Del Norte Province.", 
  "relationships": [], 
  "resources": [
    {
      "cache_last_updated": null, 
      "cache_url": null, 
      "created": "2015-12-17T11:22:45.547693", 
      "description": "", 
      "format": "CSV", 
      "hash": "", 
      "id": "c421a847-8659-43dc-a719-6651050bff8e", 
      "last_modified": null, 
      "mimetype": null, 
      "mimetype_inner": null, 
      "name": "2014 Quarter 3 - Surigao Del Norte Province IRAU", 
      "package_id": "30d64e00-99cd-435b-9e66-969a689fa300", 
      "position": 0, 
      "resource_group_id": "2d3c30d8-771f-4e41-a96e-629857a0dda3", 
      "resource_type": null, 
      "size": null, 
      "url": "http://storage.googleapis.com/amt-dgph.appspot.com/uploads/QRomxtuyZNd7EdKiiqkl/surigaodelnorte_ira_utilization_20%_09302014_q3.csv", 
      "url_type": null, 
      "webstore_last_updated": null, 
      "webstore_url": null
    }, 
    {
      "cache_last_updated": null, 
      "cache_url": null, 
      "created": "2015-12-17T11:22:57.915363", 
      "description": "", 
      "format": "CSV", 
      "hash": "", 
      "id": "d5fb9738-b404-4722-be6d-95a26a3f5330", 
      "last_modified": null, 
      "mimetype": null, 
      "mimetype_inner": null, 
      "name": "2012 Quarter 2 - Surigao Del Norte Province IRAU", 
      "package_id": "30d64e00-99cd-435b-9e66-969a689fa300", 
      "position": 1, 
      "resource_group_id": "2d3c30d8-771f-4e41-a96e-629857a0dda3", 
      "resource_type": null, 
      "size": null, 
      "url": "http://storage.googleapis.com/amt-dgph.appspot.com/uploads/4SIVxbtl3oNHMYGDk1ls/surigao_del_norte_ira_utilization_20120630_q2.csv", 
      "url_type": null, 
      "webstore_last_updated": null, 
      "webstore_url": null
    }, 
    {
      "cache_last_updated": null, 
      "cache_url": null, 
      "created": "2015-12-17T11:23:02.012573", 
      "description": "", 
      "format": "CSV", 
      "hash": "", 
      "id": "d30bb205-d02d-4a4e-9e80-93c81e2f1839", 
      "last_modified": null, 
      "mimetype": null, 
      "mimetype_inner": null, 
      "name": "2012 Quarter 1 - Surigao Del Norte Province IRAU", 
      "package_id": "30d64e00-99cd-435b-9e66-969a689fa300", 
      "position": 2, 
      "resource_group_id": "2d3c30d8-771f-4e41-a96e-629857a0dda3", 
      "resource_type": null, 
      "size": null, 
      "url": "http://storage.googleapis.com/amt-dgph.appspot.com/uploads/SPnDCCwBbkIY7QphGhpA/surigao_del_norte_ira_utilization_20120331_q1.csv", 
      "url_type": null, 
      "webstore_last_updated": null, 
      "webstore_url": null
    }, 
    {
      "cache_last_updated": null, 
      "cache_url": null, 
      "created": "2015-12-17T11:23:06.531425", 
      "description": "", 
      "format": "CSV", 
      "hash": "", 
      "id": "e1fd2cd9-e27b-4073-b918-92e2ee91158e", 
      "last_modified": null, 
      "mimetype": null, 
      "mimetype_inner": null, 
      "name": "2013 Quarter 4 - Surigao Del Norte Province IRAU", 
      "package_id": "30d64e00-99cd-435b-9e66-969a689fa300", 
      "position": 3, 
      "resource_group_id": "2d3c30d8-771f-4e41-a96e-629857a0dda3", 
      "resource_type": null, 
      "size": null, 
      "url": "http://storage.googleapis.com/amt-dgph.appspot.com/uploads/KtZuBarAWrEmomDRRVmv/surigao_del_norte_ira_utilization_20131231_q4_1.csv", 
      "url_type": null, 
      "webstore_last_updated": null, 
      "webstore_url": null
    }, 
    {
      "cache_last_updated": null, 
      "cache_url": null, 
      "created": "2015-12-17T11:23:10.164314", 
      "description": "", 
      "format": "CSV", 
      "hash": "", 
      "id": "92bc43e4-b0f4-4597-846a-3c0f1dc63aa0", 
      "last_modified": null, 
      "mimetype": null, 
      "mimetype_inner": null, 
      "name": "2013 Quarter 3 - Surigao Del Norte Province IRAU", 
      "package_id": "30d64e00-99cd-435b-9e66-969a689fa300", 
      "position": 4, 
      "resource_group_id": "2d3c30d8-771f-4e41-a96e-629857a0dda3", 
      "resource_type": null, 
      "size": null, 
      "url": "http://storage.googleapis.com/amt-dgph.appspot.com/uploads/EWbrW0xCcv0AmFG7s8xl/surigao_del_norte_ira_utilization_20130930_q3_1.csv", 
      "url_type": null, 
      "webstore_last_updated": null, 
      "webstore_url": null
    }, 
    {
      "cache_last_updated": null, 
      "cache_url": null, 
      "created": "2015-12-17T11:23:13.816556", 
      "description": "", 
      "format": "CSV", 
      "hash": "", 
      "id": "4d38eb8c-7069-4876-9ea6-3b5de2693c05", 
      "last_modified": null, 
      "mimetype": null, 
      "mimetype_inner": null, 
      "name": "2014 Quarter 2 - Surigao Del Norte Province IRAU", 
      "package_id": "30d64e00-99cd-435b-9e66-969a689fa300", 
      "position": 5, 
      "resource_group_id": "2d3c30d8-771f-4e41-a96e-629857a0dda3", 
      "resource_type": null, 
      "size": null, 
      "url": "http://storage.googleapis.com/amt-dgph.appspot.com/uploads/sQztfiQOwk0KEZOLJZBx/surigaodelnorte_ira_utilization_20%_06302014_q2.csv", 
      "url_type": null, 
      "webstore_last_updated": null, 
      "webstore_url": null
    }, 
    {
      "cache_last_updated": null, 
      "cache_url": null, 
      "created": "2015-12-17T11:23:18.060756", 
      "description": "", 
      "format": "CSV", 
      "hash": "", 
      "id": "d21c0acf-9382-4fd6-a681-7e0e0a14fbd9", 
      "last_modified": null, 
      "mimetype": null, 
      "mimetype_inner": null, 
      "name": "2013 Quarter 2  - Surigao Del Norte Province IRAU", 
      "package_id": "30d64e00-99cd-435b-9e66-969a689fa300", 
      "position": 6, 
      "resource_group_id": "2d3c30d8-771f-4e41-a96e-629857a0dda3", 
      "resource_type": null, 
      "size": null, 
      "url": "http://storage.googleapis.com/amt-dgph.appspot.com/uploads/Fi3XbTNTugMJWx6ZVsba/surigao_del_norte_ira_utilization_20130630_q2_1.csv", 
      "url_type": null, 
      "webstore_last_updated": null, 
      "webstore_url": null
    }, 
    {
      "cache_last_updated": null, 
      "cache_url": null, 
      "created": "2015-12-17T11:23:21.740514", 
      "description": "", 
      "format": "CSV", 
      "hash": "", 
      "id": "ca508040-7e92-4229-87ff-28b2bec10695", 
      "last_modified": null, 
      "mimetype": null, 
      "mimetype_inner": null, 
      "name": "2013 Quarter 1 - Surigao Del Norte Province IRAU", 
      "package_id": "30d64e00-99cd-435b-9e66-969a689fa300", 
      "position": 7, 
      "resource_group_id": "2d3c30d8-771f-4e41-a96e-629857a0dda3", 
      "resource_type": null, 
      "size": null, 
      "url": "http://storage.googleapis.com/amt-dgph.appspot.com/uploads/X8IiTCwXXtPFqbnUrEkW/surigao_del_norte_ira_utilization_20130131_q1_1.csv", 
      "url_type": null, 
      "webstore_last_updated": null, 
      "webstore_url": null
    }, 
    {
      "cache_last_updated": null, 
      "cache_url": null, 
      "created": "2015-12-17T11:23:25.724001", 
      "description": "", 
      "format": "CSV", 
      "hash": "", 
      "id": "88b92b04-e148-4d3f-83dd-e07d8deb6a8f", 
      "last_modified": null, 
      "mimetype": null, 
      "mimetype_inner": null, 
      "name": "2014 Quarter 1 - Surigao Del Norte Province IRAU", 
      "package_id": "30d64e00-99cd-435b-9e66-969a689fa300", 
      "position": 8, 
      "resource_group_id": "2d3c30d8-771f-4e41-a96e-629857a0dda3", 
      "resource_type": null, 
      "size": null, 
      "url": "http://storage.googleapis.com/amt-dgph.appspot.com/uploads/dSE0jBQHvVZq1ARBALsd/surigaodelnorte_ira_utilization_20%_03312014_q1.csv", 
      "url_type": null, 
      "webstore_last_updated": null, 
      "webstore_url": null
    }
  ], 
  "tags": [
    "Local Government"
  ], 
  "title": "INTERNAL REVENUE ALLOTMENT UTILIZATION OF SURIGAO DEL NORTE PROVINCE", 
  "url": "", 
  "version": ""
}